mplabml/__init__.py
mplabml/client.py
mplabml/datasets.py
mplabml/ml_runner.py
mplabml/model_runner.py
mplabml/pipeline.py
mplabml/render.py
mplabml/sml_runner.py
mplabml/base/__init__.py
mplabml/base/exceptions.py
mplabml/base/snippets.py
mplabml/base/utility.py
mplabml/connection/__init__.py
mplabml/connection/connection.py
mplabml/connection/connection_config.py
mplabml/connection/errors.py
mplabml/data/__init__.py
mplabml/datamanager/__init__.py
mplabml/datamanager/base.py
mplabml/datamanager/capture.py
mplabml/datamanager/capture_configuration.py
mplabml/datamanager/capture_configurations.py
mplabml/datamanager/captures.py
mplabml/datamanager/clientplatformdescription.py
mplabml/datamanager/clientplatformdescriptions.py
mplabml/datamanager/confusion_matrix.py
mplabml/datamanager/custom_functions.py
mplabml/datamanager/deviceconfig.py
mplabml/datamanager/errors.py
mplabml/datamanager/featurefile.py
mplabml/datamanager/featurefiles.py
mplabml/datamanager/foundation_model.py
mplabml/datamanager/function.py
mplabml/datamanager/functions.py
mplabml/datamanager/knowledgepack.py
mplabml/datamanager/label.py
mplabml/datamanager/label_relationship.py
mplabml/datamanager/labelvalue.py
mplabml/datamanager/library_pack.py
mplabml/datamanager/metadata.py
mplabml/datamanager/metadata_relationship.py
mplabml/datamanager/metadata_value.py
mplabml/datamanager/modelresults.py
mplabml/datamanager/pipeline.py
mplabml/datamanager/project.py
mplabml/datamanager/projects.py
mplabml/datamanager/queries.py
mplabml/datamanager/query.py
mplabml/datamanager/sandbox.py
mplabml/datamanager/sandboxes.py
mplabml/datamanager/segment.py
mplabml/datamanager/segmenter.py
mplabml/datamanager/team.py
mplabml/dclproj/__init__.py
mplabml/dclproj/confusion_matrix.py
mplabml/dclproj/csv_to_dcli.py
mplabml/dclproj/datasegments.py
mplabml/dclproj/dclproj.py
mplabml/dclproj/upload.py
mplabml/dclproj/utils.py
mplabml/dclproj/vizualization.py
mplabml/image/__init__.py
mplabml/method_calls/__init__.py
mplabml-2025.1.2.dist-info/LICENSE
mplabml-2025.1.2.dist-info/METADATA
mplabml-2025.1.2.dist-info/WHEEL
mplabml-2025.1.2.dist-info/top_level.txt
mplabml-2025.1.2.dist-info/RECORD
