Metadata-Version: 2.1
Name: mplabml
Version: 2025.1.2
Summary: MPLABML Python SDK
Author: Microchip
Author-email: nicholas.copeland@microchip.com
License: Proprietary
Classifier: Operating System :: OS Independent
Classifier: Programming Language :: Python :: 3.6
Classifier: Programming Language :: Python :: 3.7
License-File: LICENSE
Requires-Dist: cookiejar ==0.0.2
Requires-Dist: requests >=2.14.2
Requires-Dist: requests-oauthlib >=0.7.0
Requires-Dist: appdirs
Requires-Dist: semantic-version >=2.6.0
Requires-Dist: numpy
Requires-Dist: pandas
Requires-Dist: matplotlib
Requires-Dist: prompt-toolkit
Requires-Dist: seaborn
Requires-Dist: wurlitzer
Requires-Dist: tabulate
Requires-Dist: scipy
